{ "height":10,
 "infinite":false,
 "layers":[
        {
         "data":[3, 3, 3, 3, 3, 3, 3, 3, 3, 3, 3, 3, 3, 3, 3, 3, 3, 3, 3, 3, 3, 0, 0, 0, 0, 0, 0, 0, 0, 0, 0, 0, 0, 0, 0, 0, 0, 0, 0, 3, 3, 0, 0, 12, 0, 0, 0, 0, 12, 0, 0, 0, 0, 0, 0, 0, 0, 0, 0, 3, 3, 0, 0, 0, 0, 0, 0, 0, 0, 0, 0, 0, 0, 0, 0, 0, 0, 0, 0, 3, 3, 0, 0, 0, 0, 0, 0, 0, 0, 0, 0, 0, 0, 0, 0, 0, 0, 0, 0, 3, 3, 0, 0, 0, 0, 0, 0, 0, 0, 0, 0, 0, 0, 0, 0, 0, 0, 0, 0, 3, 3, 0, 0, 7, 7, 0, 0, 0, 0, 0, 0, 0, 0, 0, 0, 0, 7, 7, 0, 3, 3, 0, 0, 0, 0, 0, 0, 0, 0, 7, 0, 0, 0, 0, 0, 0, 0, 0, 0, 3, 3, 0, 0, 0, 0, 0, 0, 1, 6, 1, 1, 0, 7, 0, 1, 6, 1, 1, 7, 3, 3, 1, 1, 1, 1, 1, 1, 3, 3, 3, 3, 1, 1, 1, 3, 3, 3, 3, 1, 3],
         "height":10,
         "name":"Tile Layer 1",
         "opacity":1,
         "type":"tilelayer",
         "visible":true,
         "width":20,
         "x":0,
         "y":0
        }, 
        {
         "draworder":"topdown",
         "name":"spawn",
         "objects":[
                {
                 "gid":23,
                 "height":64,
                 "id":1,
                 "name":"",
                 "rotation":0,
                 "type":"",
                 "visible":true,
                 "width":64,
                 "x":204.204643682782,
                 "y":190.809930646296
                }, 
                {
                 "gid":23,
                 "height":64,
                 "id":2,
                 "name":"",
                 "rotation":0,
                 "type":"",
                 "visible":true,
                 "width":64,
                 "x":169.025228666198,
                 "y":326.501959995979
                }, 
                {
                 "gid":23,
                 "height":64,
                 "id":3,
                 "name":"",
                 "rotation":0,
                 "type":"",
                 "visible":true,
                 "width":64,
                 "x":84.5946326263946,
                 "y":576.778369685395
                }, 
                {
                 "gid":23,
                 "height":64,
                 "id":4,
                 "name":"spawn",
                 "rotation":0,
                 "type":"",
                 "visible":true,
                 "width":64,
                 "x":170.030354809529,
                 "y":378.768519449191
                }, 
                {
                 "gid":23,
                 "height":64,
                 "id":5,
                 "name":"",
                 "rotation":0,
                 "type":"",
                 "visible":true,
                 "width":64,
                 "x":214.255905116092,
                 "y":371.732636445874
                }, 
                {
                 "gid":23,
                 "height":64,
                 "id":6,
                 "name":"",
                 "rotation":0,
                 "type":"",
                 "visible":true,
                 "width":64,
                 "x":118.768921499648,
                 "y":404.901799175796
                }, 
                {
                 "gid":29,
                 "height":64,
                 "id":7,
                 "name":"",
                 "rotation":0,
                 "type":"",
                 "visible":true,
                 "width":64,
                 "x":55.445974469796,
                 "y":549.639963815459
                }, 
                {
                 "gid":29,
                 "height":64,
                 "id":8,
                 "name":"",
                 "rotation":0,
                 "type":"",
                 "visible":true,
                 "width":64,
                 "x":94.6458940597045,
                 "y":594.870640265353
                }, 
                {
                 "gid":29,
                 "height":64,
                 "id":9,
                 "name":"",
                 "rotation":0,
                 "type":"",
                 "visible":true,
                 "width":64,
                 "x":56.4511006131269,
                 "y":566.727108252086
                }, 
                {
                 "gid":29,
                 "height":64,
                 "id":10,
                 "name":"",
                 "rotation":0,
                 "type":"",
                 "visible":true,
                 "width":64,
                 "x":81.5792541964016,
                 "y":577.783495828726
                }],
         "opacity":1,
         "type":"objectgroup",
         "visible":true,
         "x":0,
         "y":0
        }],
 "nextobjectid":11,
 "orientation":"orthogonal",
 "renderorder":"right-down",
 "tiledversion":"1.1.6",
 "tileheight":64,
 "tilesets":[
        {
         "firstgid":1,
         "source":"..\/..\/assets\/tile_3.tsx"
        }],
 "tilewidth":64,
 "type":"map",
 "version":1,
 "width":20
}